agnt/__init__.py
agnt-0.7.12.dist-info/METADATA
agnt-0.7.12.dist-info/WHEEL
agnt-0.7.12.dist-info/entry_points.txt
agnt-0.7.12.dist-info/licenses/LICENSE
agnt-0.7.12.dist-info/RECORD
