Metadata-Version: 2.4
Name: agnt
Version: 0.7.12
Summary: MCP server for AI coding agents - process management, reverse proxy with traffic logging, browser instrumentation, and sketch mode
Project-URL: Homepage, https://standardbeagle.github.io/agnt/
Project-URL: Documentation, https://standardbeagle.github.io/agnt/
Project-URL: Repository, https://github.com/standardbeagle/agnt
Project-URL: Issues, https://github.com/standardbeagle/agnt/issues
Project-URL: Changelog, https://github.com/standardbeagle/agnt/blob/main/CHANGELOG.md
Author-email: Standard Beagle <dev@standardbeagle.com>
License-Expression: MIT
License-File: LICENSE
Keywords: agent,ai,claude-code,debugging,development,devtools,diagnostics,frontend,mcp,model-context-protocol,process-management,proxy,sketch,wireframe
Classifier: Development Status :: 4 - Beta
Classifier: Environment :: Console
Classifier: Intended Audience :: Developers
Classifier: License :: OSI Approved :: MIT License
Classifier: Operating System :: MacOS
Classifier: Operating System :: Microsoft :: Windows
Classifier: Operating System :: POSIX :: Linux
Classifier: Programming Language :: Python :: 3
Classifier: Programming Language :: Python :: 3.10
Classifier: Programming Language :: Python :: 3.11
Classifier: Programming Language :: Python :: 3.12
Classifier: Topic :: Internet :: Proxy Servers
Classifier: Topic :: Software Development :: Debuggers
Classifier: Topic :: Software Development :: Testing
Requires-Python: >=3.10
Requires-Dist: httpx>=0.25.0
